{ 
  "cable-9C6L4-E3-VI-1000": {
    "pageTitle": "Rollo de 305 metros de cable UTP sólido 04 pares  Cat 6 23AWG LSZH, IEC 60332-1 color Violeta. marca SIEMON 9C6L4-E3-VI-1000",
    "titulo": "Rollo de 305 metros de cable UTP sólido 04 pares  Cat 6 23AWG LSZH, IEC 60332-1 color Violeta. marca SIEMON 9C6L4-E3-VI-1000",
    "precio": "U$ 438",
    "imagenes": [
      "https://web.netperu100.com/siemon/images/9C6L4-E3-VI-1000_front.webp",
      "https://web.netperu100.com/siemon/images/9C6L4-E3-VI-1000_sid.webp",
      "https://web.netperu100.com/siemon/images/9C6L4-E3-VI-1000_sid.webp"
    ],
    "especificaciones": [
      "Cable Category 6 UTP (sin blindaje), diseño Solution 6 LSZH-1 con chaqueta violeta y marcado inverso en secuencia",
      "Conductores sólidos de 24 AWG (≈ 0.52 mm), aislamiento HDPE ≈ 0.99 mm",
      "Miembro central de aislamiento (“cross-pair separator”) para mejorar geometría interna y reducir diafonía",
      "Diámetro exterior nominal de ≈ 5.6 mm (± tolerancia)",
      "Chaqueta LSZH (Clase Eca) cumpliendo LSOH y IEC flame tests (incluye IEC 60332-3-22, IEC 60754, IEC 61034)"
    ],
    "detalles": [
      {
        "titulo": "Especificaciones Técnicas",
        "items": [
          {
            "label": "Tipo de dispositivo:",
            "value": "cable de infraestructura Category 6 UTP, versión Solution 6, 4 pares sólidos 24 AWG, chaqueta LSZH tipo L (violeta)"
          },
          {
            "label": "Conectividad:",
            "value": "compatible con 10BASE-T, 100BASE-T, 1000BASE-T, soporte para PoE IEEE 802.3af/at/bt (tipos 1-4) y Power over HDBaseT (PoH)"
          },
          {
            "label": "Dimensiones:",
            "value": "diámetro exterior nominal ≈ 5.6 mm (0.22 in.); aislamiento ~0.99 mm; conductor ~0.52 mm"
          },
          {
            "label": "Peso:",
            "value": "No especificado"
          }
        ]
      },
      {
        "titulo": "Protocolos Soportados",
        "items": [
          {
            "label": "Protocolo de direccionamiento:",
            "value": "Ethernet estándar 10/100/1000BASE-T (Cat 6 hasta 250 MHz)"
          },
          {
            "label": "Protocolo de gestión remota:",
            "value": "No aplicable al cable; se gestiona desde switches o sistemas de NMS."
          }
        ]
      },
      {
        "titulo": "Cumplimiento de Normas",
        "items": [
          {
            "label": "",
            "value": "Cumple ANSI/TIA-568.2-D, ISO/IEC 11801-1 Ed 1.0 (Clase E) y IEC 61156-5 (Category 6), Estándares de PoE compatibles IEEE 802.3af/at/bt y PoH"
          }
        ]
      },
      {
        "titulo": "Certificaciones y Ambiente",
        "items": [
          {
            "label": "Certificaciones:",
            "value": "LSZH tipo L (IEC 60332-1 y 60332-3-22), IEC 60754-1/2, IEC 61034; Euro-Clase CPR Clase Eca (según EN 50575)"
          },
          {
            "label": "Temperatura de operación:",
            "value": "Instalación: 5…60 °C (41…140 °F), Operación: -10…60 °C (14…140 °F), Almacenamiento: 0…60 °C (32…140 °F)"
          }
        ]
      }
    ],
    "descargas": [
      {
        "tipo": "Ficha técnica ",
        "url": "https://nelsonmendez871.github.io/MULTIMEDIA/Pdf/9A6L4-A5/9A6L4-A5_ds.pdf",
        "icono": "fas fa-file-pdf",
        "color": "text-red-500"
      },
      {
        "tipo": "Manual",
        "url": "https://nelsonmendez871.github.io/MULTIMEDIA/Pdf/9A6L4-A5/9A6L4-A5_ds.pdf",
        "icono": "fas fa-book-open",
        "color": "text-blue-500"
      },
      {
        "tipo": "Especificaciones",
        "url": "https://nelsonmendez871.github.io/MULTIMEDIA/Pdf/9A6L4-A5/9A6L4-A5_ds.pdf",
        "icono": "fas fa-file-alt",
        "color": "text-green-500"
      }
    ]
  },

  "cable-9C6L4-E2": {
    "pageTitle": "Rollo de 305 metros de cable UTP sólido de 04 pares Cat 6 23 AWG LSZH-3, color violeta, marca SIEMON 9C6L4-E2",
    "titulo": "Rollo de 305 metros de cable UTP sólido de 04 pares Cat 6 23 AWG LSZH-3, color violeta, marca SIEMON 9C6L4-E2",
    "precio": "U$ 212",
    "imagenes": [
      "https://web.netperu100.com/siemon/images/9C6J4-E3_top.webp",
      "https://web.netperu100.com/siemon/images/9C6J4-E3_front.webp",
      "https://web.netperu100.com/siemon/images/9C6J4-E3_top.webp"
    ],
    "especificaciones": [
      "Cable Category 6 UTP (sin blindaje), diseño Solution 6 LSZH-1 con chaqueta violeta y marcado inverso en secuencia",
      "Conductores sólidos de 24 AWG (≈ 0.52 mm), aislamiento HDPE ≈ 0.99 mm",
      "Miembro central de aislamiento (“cross-pair separator”) para mejorar geometría interna y reducir diafonía",
      "Diámetro exterior nominal de ≈ 5.6 mm (± tolerancia)",
      "Chaqueta LSZH (Clase Eca) cumpliendo LSOH y IEC flame tests (incluye IEC 60332-3-22, IEC 60754, IEC 61034)"
    ],
    "detalles": [
      {
        "titulo": "Especificaciones Técnicas",
        "items": [
          {
            "label": "Tipo de dispositivo:",
            "value": "cable de infraestructura Category 6 UTP, versión Solution 6, 4 pares sólidos 24 AWG, chaqueta LSZH tipo L (violeta)"
          },
          {
            "label": "Conectividad:",
            "value": "compatible con 10BASE-T, 100BASE-T, 1000BASE-T, soporte para PoE IEEE 802.3af/at/bt (tipos 1-4) y Power over HDBaseT (PoH)"
          },
          {
            "label": "Dimensiones:",
            "value": "diámetro exterior nominal ≈ 5.6 mm (0.22 in.); aislamiento ~0.99 mm; conductor ~0.52 mm"
          },
          {
            "label": "Peso:",
            "value": "No especificado"
          }
        ]
      },
      {
        "titulo": "Protocolos Soportados",
        "items": [
          {
            "label": "Protocolo de direccionamiento:",
            "value": "Ethernet estándar 10/100/1000BASE-T (Cat 6 hasta 250 MHz)"
          },
          {
            "label": "Protocolo de gestión remota:",
            "value": "No aplicable al cable; se gestiona desde switches o sistemas de NMS."
          }
        ]
      },
      {
        "titulo": "Cumplimiento de Normas",
        "items": [
          {
            "label": "",
            "value": "Cumple ANSI/TIA-568.2-D, ISO/IEC 11801-1 Ed 1.0 (Clase E) y IEC 61156-5 (Category 6), Estándares de PoE compatibles IEEE 802.3af/at/bt y PoH"
          }
        ]
      },
      {
        "titulo": "Certificaciones y Ambiente",
        "items": [
          {
            "label": "Certificaciones:",
            "value": "LSZH tipo L (IEC 60332-1 y 60332-3-22), IEC 60754-1/2, IEC 61034; Euro-Clase CPR Clase Eca (según EN 50575)"
          },
          {
            "label": "Temperatura de operación:",
            "value": "Instalación: 5…60 °C (41…140 °F), Operación: -10…60 °C (14…140 °F), Almacenamiento: 0…60 °C (32…140 °F)"
          }
        ]
      }
    ],
    "descargas": [
      {
        "tipo": "Ficha técnica ",
        "url": "https://nelsonmendez871.github.io/MULTIMEDIA/Pdf/9A6L4-A5/9A6L4-A5_ds.pdf",
        "icono": "fas fa-file-pdf",
        "color": "text-red-500"
      },
      {
        "tipo": "Manual",
        "url": "https://nelsonmendez871.github.io/MULTIMEDIA/Pdf/9A6L4-A5/9A6L4-A5_ds.pdf",
        "icono": "fas fa-book-open",
        "color": "text-blue-500"
      },
      {
        "tipo": "Especificaciones",
        "url": "https://nelsonmendez871.github.io/MULTIMEDIA/Pdf/9A6L4-A5/9A6L4-A5_ds.pdf",
        "icono": "fas fa-file-alt",
        "color": "text-green-500"
      }
    ]
  },

  "cable-9C6J4-E3": {
    "pageTitle": "Rollo de 305 metros de cable UTP sólido de 04 pares Cat 6 23 AWG LSZH-3, color violeta, marca SIEMON 9C6J4-E3",
    "titulo": "Rollo de 305 metros de cable UTP sólido de 04 pares Cat 6 23 AWG LSZH-3, color violeta, marca SIEMON 9C6J4-E3",
    "precio": "U$ 481",
    "imagenes": [
      "https://web.netperu100.com/siemon/images/9C6J4-E3_top.webp",
      "https://web.netperu100.com/siemon/images/9C6J4-E3_front.webp",
      "https://web.netperu100.com/siemon/images/9C6J4-E3_top.webp"
    ],
    "especificaciones": [
      "Cable Category 6 UTP (sin blindaje), 4 pares trenzados con miembro central de aislamiento (“center isolation member”) para geometría y reducción de diafonía",
      "Conductor: cobre sólido 23 AWG (~0.55 mm), aislamiento de HDPE (~0.99 mm)",
      "Chaqueta LSZH tipo LSOH-3C, violeta, diseñada para cumplir exigentes estándares de inflamabilidad IEC 60332-3C para cables agrupados",
      "Diámetro exterior nominal: ~6.20 mm (0.24 in, máximo)"
    ],
    "detalles": [
      {
        "titulo": "Especificaciones Técnicas",
        "items": [
          {
            "label": "Tipo de dispositivo:",
            "value": "Cable de infraestructura Category 6 UTP sólido, diseño System 6 para alto rendimiento"
          },
          {
            "label": "Conectividad:",
            "value": "Compatible con 10BASE-T, 100BASE-T, 1000BASE-T; soporta PoE IEEE 802.3af (Tipo 1), at (Tipo 2), bt (Tipo 3 y 4) y Power over HDBaseT (PoH)"
          },
          {
            "label": "Dimensiones:",
            "value": "Diámetro exterior ~6.20 mm; aislamiento ~0.99 mm; conductor ~0.55 mm (23 AWG)"
          },
          {
            "label": "Peso:",
            "value": "No especificado"
          }
        ]
      },
      {
        "titulo": "Protocolos Soportados",
        "items": [
          {
            "label": "Protocolo de direccionamiento:",
            "value": "Estándares Ethernet 10/100/1000BASE-T y Category 6 activas hasta 250 MHz (rendimiento garantizado conforme a ISO/TIA)"
          },
          {
            "label": "Protocolo de gestión remota:",
            "value": "No aplicable al cable; se gestiona desde switches o sistemas de NMS."
          }
        ]
      },
      {
        "titulo": "Cumplimiento de Normas",
        "items": [
          {
            "label": "",
            "value": "Cumple con ISO/IEC 11801-1 Ed.1.0 (Clase E) para Category 6, Cumple ANSI/TIA-568.2-D (Categoría 6), Cumple IEC 61156-5 para cables Category 6, Estándares de fuego LS0H: IEC 60332-3-24, IEC 60332-3-25, además de IEC 60754-2 y IEC 61034; certificación CPR Clase Eca / Dca s2 d2 a1, Cumple normas IEEE para PoE: 802.3af/at/bt y PoH"
          }
        ]
      },
      {
        "titulo": "Certificaciones y Ambiente",
        "items": [
          {
            "label": "Certificaciones:",
            "value": "LSOH tipo LSOH-3C según IEC 60332-3C (agrupados), IEC 60332-3-24/-3-25, IEC 60754-2, IEC 61034; CPR Clase Eca / Dca s2 d2 a1"
          },
          {
            "label": "Temperatura de operación:",
            "value": "desde -20 °C hasta +60 °C; temperatura de instalación: 0 a 60 °C; almacenamiento: -20 a +75 °C"
          }
        ]
      }
    ],
    "descargas": [
      {
        "tipo": "Ficha técnica ",
        "url": "https://nelsonmendez871.github.io/MULTIMEDIA/Pdf/9A6L4-A5/9A6L4-A5_ds.pdf",
        "icono": "fas fa-file-pdf",
        "color": "text-red-500"
      },
      {
        "tipo": "Manual",
        "url": "https://nelsonmendez871.github.io/MULTIMEDIA/Pdf/9A6L4-A5/9A6L4-A5_ds.pdf",
        "icono": "fas fa-book-open",
        "color": "text-blue-500"
      },
      {
        "tipo": "Especificaciones",
        "url": "https://nelsonmendez871.github.io/MULTIMEDIA/Pdf/9A6L4-A5/9A6L4-A5_ds.pdf",
        "icono": "fas fa-file-alt",
        "color": "text-green-500"
      }
    ]
  },

  "cable-9C6L4-A5": {
    "pageTitle": "Rollo de 305 metros de cable UTP sólido 04 pares Cat 6A 23AWG LSZH color Violeta, marca SIEMON 9C6L4-A5",
    "titulo": "Rollo de 305 metros de cable UTP sólido 04 pares Cat 6A 23AWG LSZH color Violeta, marca SIEMON 9C6L4-A5",
    "precio": "U$ 764",
    "imagenes": [
      "https://web.netperu100.com/siemon/images/9C6L4-A5_left.webp",
      "https://web.netperu100.com/siemon/images/9C6L4-A5_front.webp",
      "https://web.netperu100.com/siemon/images/9C6L4-A5_sid.webp"
    ],
    "especificaciones": [
      "Cable categoría 6A UTP (unshielded), LSZH (bajo humo y sin halógenos)",
      "4 pares trenzados con conductor sólido de cobre 23 AWG (0.57 mm)",
      "Miembro central de aislamiento (cross-separator) para mantener geometría y reducir diafonía",
      "Cubierta de aluminio con cable de drenaje de cobre estañado (~0.50 mm)",
      "Diámetro exterior nominal ~6.99 mm (±0.3 mm)",
      "Clasificación de temperatura 75 °C"
    ],
    "detalles": [
      {
        "titulo": "Especificaciones Técnicas",
        "items": [
          {
            "label": "Tipo de dispositivo:",
            "value": "cable de par trenzado apantallado F/UTP (foil-shielded) para infraestructura de red categoría 6A"
          },
          {
            "label": "Conectividad:",
            "value": "transmisiones Ethernet hasta 10GBASE-T / 1000BASE-T / 100BASE-T / 10BASE-T, soporte para PoE (IEEE 802.3af/at/bt) y Power over HDBaseT (PoH)"
          },
          {
            "label": "Dimensiones:",
            "value": "Diámetro exterior: ~6.99 mm (~7.0 mm)"
          },
          {
            "label": "Peso:",
            "value": "aproximado: 20 kg por rollo de 305 m (~44 lb)"
          }
        ]
      },
      {
        "titulo": "Protocolos Soportados",
        "items": [
          {
            "label": "Protocolo de direccionamiento:",
            "value": "compatible con protocolos estándares de Ethernet (10BASE-T, 100BASE-T, 1000BASE-T, 10GBASE-T)."
          },
          {
            "label": "Protocolo de gestión remota:",
            "value": "no aplica directamente al cable; La gestión remota sería gestionada por switch/NMS, no por cable."
          }
        ]
      },
      {
        "titulo": "Cumplimiento de Normas",
        "items": [
          {
            "label": "",
            "value": "Cumple con ANSI/TIA-568.2-D para cables Cat6A, Cumple ISO/IEC 11801-1 Clase EA (Cat6A global), IEC 61156-5 Ed.2.0 (Especificación para cables de par trenzado), IEC 60332-3-24 y IEC 60332-3-25 (resistencia al fuego de cables en instalaciones), IEC 60754-1/2 y IEC 61034 (LSOH, baja emisión de humos y acidez)"
          }
        ]
      },
      {
        "titulo": "Certificaciones y Ambiente",
        "items": [
          {
            "label": "Certificaciones:",
            "value": "LSOH conforme a IEC 60332-3, IEC 60754, IEC 61034 y norma CPR clase Eca (según Europa)"
          },
          {
            "label": "Temperatura de operación:",
            "value": "desde -20 °C hasta +75 °C (máximo +75 °C para versión LSOH) y almacenamiento hasta +75 °C; instalación entre 0 y 60 °C"
          }
        ]
      }
    ],
    "descargas": [
      {
        "tipo": "Ficha técnica ",
        "url": "https://nelsonmendez871.github.io/MULTIMEDIA/Pdf/9A6L4-A5/9A6L4-A5_ds.pdf",
        "icono": "fas fa-file-pdf",
        "color": "text-red-500"
      },
      {
        "tipo": "Manual",
        "url": "https://nelsonmendez871.github.io/MULTIMEDIA/Pdf/9A6L4-A5/9A6L4-A5_ds.pdf",
        "icono": "fas fa-book-open",
        "color": "text-blue-500"
      },
      {
        "tipo": "Especificaciones",
        "url": "https://nelsonmendez871.github.io/MULTIMEDIA/Pdf/9A6L4-A5/9A6L4-A5_ds.pdf",
        "icono": "fas fa-file-alt",
        "color": "text-green-500"
      }
    ]
  },

  "cable-9A6J4-A5": {
    "pageTitle": "Rollo de 305 metros de cable F/UTP sólido 04 pares Cat 6A 23AWG LSZH, IEC 60332-3 color Violeta, marca SIEMON 9A6J4-A5",
    "titulo": "Rollo de 305 metros de cable F/UTP sólido 04 pares Cat 6A 23AWG LSZH, IEC 60332-3 color Violeta, marca SIEMON 9A6J4-A5",
    "precio": "U$ 469",
    "imagenes": [
      "https://web.netperu100.com/siemon/images/9A6J4-A5_sid.webp",
      "https://web.netperu100.com/siemon/images/9A6J4-A5_front.webp",
      "https://web.netperu100.com/siemon/images/9A6J4-A5_left.webp"
    ],
    "especificaciones": [
      "Cable F/UTP de 4 pares",
      "Conductor: cobre sólido de 23 AWG (0.57 mm)",
      "Marcado secuencial inverso en la cubierta para facilidad de corte y medición",
      "Cinta de aluminio como blindaje (conductor de drenaje estañado)",
      "Tecnología PowerGUARD: mejora la disipación de calor para PoE",
      "Soporta aplicaciones IP emergentes: VoIP, video IP, 10GBASE-T"
    ],
    "detalles": [
      {
        "titulo": "Especificaciones Técnicas",
        "items": [
          {
            "label": "Tipo de dispositivo:",
            "value": "cable de par trenzado apantallado F/UTP (foil-shielded) para infraestructura de red categoría 6A"
          },
          {
            "label": "Conectividad:",
            "value": "transmisiones Ethernet hasta 10GBASE-T / 1000BASE-T / 100BASE-T / 10BASE-T, soporte para PoE (IEEE 802.3af/at/bt) y Power over HDBaseT (PoH)"
          },
          {
            "label": "Dimensiones:",
            "value": "Diámetro exterior: ~6.99 mm (~7.0 mm)"
          },
          {
            "label": "Peso:",
            "value": "aproximado: 20 kg por rollo de 305 m (~44 lb)"
          }
        ]
      },
      {
        "titulo": "Protocolos Soportados",
        "items": [
          {
            "label": "Protocolo de direccionamiento:",
            "value": "compatible con protocolos estándares de Ethernet (10BASE-T, 100BASE-T, 1000BASE-T, 10GBASE-T)."
          },
          {
            "label": "Protocolo de gestión remota:",
            "value": "no aplica directamente al cable; La gestión remota sería gestionada por switch/NMS, no por cable."
          }
        ]
      },
      {
        "titulo": "Cumplimiento de Normas",
        "items": [
          {
            "label": "",
            "value": "Cumple con ANSI/TIA-568.2-D para cables Cat6A, Cumple ISO/IEC 11801-1 Clase EA (Cat6A global), IEC 61156-5 Ed.2.0 (Especificación para cables de par trenzado), IEC 60332-3-24 y IEC 60332-3-25 (resistencia al fuego de cables en instalaciones), IEC 60754-1/2 y IEC 61034 (LSOH, baja emisión de humos y acidez)"
          }
        ]
      },
      {
        "titulo": "Certificaciones y Ambiente",
        "items": [
          {
            "label": "Certificaciones:",
            "value": "LSOH conforme a IEC 60332-3, IEC 60754, IEC 61034 y norma CPR clase Eca (según Europa)"
          },
          {
            "label": "Temperatura de operación:",
            "value": "desde −20 °C hasta +75 °C (máximo +75 °C para versión LSOH) y almacenamiento hasta +75 °C; instalación entre 0 y 60 °C"
          }
        ]
      }
    ],
    "descargas": [
      {
        "tipo": "Ficha técnica ",
        "url": "https://nelsonmendez871.github.io/MULTIMEDIA/Pdf/9A6L4-A5/9A6L4-A5_ds.pdf",
        "icono": "fas fa-file-pdf",
        "color": "text-red-500"
      },
      {
        "tipo": "Manual",
        "url": "https://nelsonmendez871.github.io/MULTIMEDIA/Pdf/9A6L4-A5/9A6L4-A5_ds.pdf",
        "icono": "fas fa-book-open",
        "color": "text-blue-500"
      },
      {
        "tipo": "Especificaciones",
        "url": "https://nelsonmendez871.github.io/MULTIMEDIA/Pdf/9A6L4-A5/9A6L4-A5_ds.pdf",
        "icono": "fas fa-file-alt",
        "color": "text-green-500"
      }
    ]
  },


  "cable-9A6L4-A5": {
    "pageTitle": "Rollo de 305 metros de cable F/UTP sólido 04 pares Cat 6A 23 AWG LSZH color Violeta, marca SIEMON 9A6L4-A5",
    "titulo": "Rollo de 305 metros de cable F/UTP sólido 04 pares Cat 6A 23 AWG LSZH color Violeta, marca SIEMON A6L4-A5",
    "precio": "U$ 304",
    "imagenes": [
      "https://nelsonmendez871.github.io/MULTIMEDIA/Imagenes/9A6L4-A5/9A6L4-A5_front.webp",
      "https://nelsonmendez871.github.io/MULTIMEDIA/Imagenes/9A6L4-A5/9A6L4-A5_left.webp",
      "https://nelsonmendez871.github.io/MULTIMEDIA/Imagenes/9A6L4-A5/9A6L4-A5_sid.webp"
    ],
    "especificaciones": [
      "Cable F/UTP de 4 pares",
      "Conductor: cobre sólido de 23 AWG (0.57 mm)",
      "Diámetro exterior nominal: 7.1 mm",
      "Miembro central de aislamiento",
      "Cinta de aluminio como blindaje (conductor de drenaje estañado)",
      "Marcado secuencial inverso en la chaqueta",
      "Tecnología PowerGUARD: mejora la disipación de calor para PoE",
      "Soporta aplicaciones IP emergentes: VoIP, video IP, 10GBASE-T"
    ],
    "detalles": [
      {
        "titulo": "Especificaciones Técnicas",
        "items": [
          {
            "label": "Tipo de dispositivo:",
            "value": "Cable F/UTP de 4 pares, Categoría 6A"
          },
          {
            "label": "Conectividad:",
            "value": "10GBASE-T, 1000BASE-T, 100BASE-T, 10BASE-T, HDBASE-T, IEEE 802.3af (PoE tipo 1), IEEE 802.3at (PoE tipo 2), IEEE 802.3bt (PoE tipo 3 y 4), Power over HDBaseT (PoH)v"
          },
          {
            "label": "Dimensiones:",
            "value": "Diámetro exterior: 7.1 mm, Diámetro del conductor: 0.57 mm"
          },
          {
            "label": "Peso:",
            "value": "No se especifica directamente el peso"
          }
        ]
      },
      {
        "titulo": "Protocolos Soportados",
        "items": [
          {
            "label": "Protocolo de direccionamiento:",
            "value": "IEEE 802.3 (Ethernet), "
          },
          {
            "label": "Protocolo de gestión remota:",
            "value": "No especificado directamente"
          }
        ]
      },
      {
        "titulo": "Cumplimiento de Normas",
        "items": [
          {
            "label": "",
            "value": "ANSI/TIA-568.2-D, IEC 61156-5 Ed 2.0, ISO/IEC 11801-1 Ed 1.0, UL CMR y CSA FT4, UL CMP y CSA FT6, CMP-LP(0.6A) 120W"
          }
        ]
      },
      {
        "titulo": "Certificaciones y Ambiente",
        "items": [
          {
            "label": "Certificaciones:",
            "value": "UL CMR y CSA FT4, UL CMP y CSA FT6"
          },
          {
            "label": "Temperatura de operación:",
            "value": "Versión CMP: -20°C a 90°C, Versión CMR: -20°C a 75°C"
          }
        ]
      }
    ],
    "descargas": [
      {
        "tipo": "Ficha técnica ",
        "url": "https://nelsonmendez871.github.io/MULTIMEDIA/Pdf/9A6L4-A5/9A6L4-A5_ds.pdf",
        "icono": "fas fa-file-pdf",
        "color": "text-red-500"
      },
      {
        "tipo": "Manual",
        "url": "https://nelsonmendez871.github.io/MULTIMEDIA/Pdf/9A6L4-A5/9A6L4-A5_ds.pdf",
        "icono": "fas fa-book-open",
        "color": "text-blue-500"
      },
      {
        "tipo": "Especificaciones",
        "url": "https://nelsonmendez871.github.io/MULTIMEDIA/Pdf/9A6L4-A5/9A6L4-A5_ds.pdf",
        "icono": "fas fa-file-alt",
        "color": "text-green-500"
      }
    ]
  }
}
